twinshare_cli.py
examples/api_usage.py
examples/rest_api_usage.py
safetytwin_share-0.1.44.dist-info/licenses/LICENSE
scripts/start_rest_api.py
src/__init__.py
src/api/__init__.py
src/api/p2p_api.py
src/api/rest_client.py
src/api/rest_server.py
src/api/server.py
src/api/vm_api.py
src/api/endpoints/__init__.py
src/api/endpoints/discovery.py
src/api/endpoints/environments.py
src/api/endpoints/workspaces.py
src/cli/__init__.py
src/cli/commands.py
src/cli/main.py
src/core/__init__.py
src/core/config.py
src/core/environment.py
src/core/project.py
src/core/workspace.py
src/p2p/__init__.py
src/p2p/discovery.py
src/p2p/network.py
src/p2p/protocol.py
src/runtime/__init__.py
src/runtime/container.py
src/runtime/process.py
src/runtime/vm.py
src/sharing/__init__.py
src/sharing/auth.py
src/sharing/repository.py
src/sharing/transfer.py
src/utils/__init__.py
src/utils/crypto.py
src/utils/logging.py
src/utils/system.py
src/web/__init__.py
src/web/server.py
tests/__init__.py
tests/unit/test_basic.py
update/changelog.py
update/config.py
update/env_manager.py
update/src.py
update/test_code.py
safetytwin_share-0.1.44.dist-info/METADATA
safetytwin_share-0.1.44.dist-info/WHEEL
safetytwin_share-0.1.44.dist-info/entry_points.txt
safetytwin_share-0.1.44.dist-info/top_level.txt
safetytwin_share-0.1.44.dist-info/RECORD
